amp4e/Auth.py
amp4e/Computers.py
amp4e/Version.py
amp4e/__init__.py
amp4e/__main__.py
amp4e/test.py
amp4e/classes/__init__.py
amp4e/classes/a.py
a4e_bmacer-0.0.8.dist-info/LICENSE
a4e_bmacer-0.0.8.dist-info/METADATA
a4e_bmacer-0.0.8.dist-info/WHEEL
a4e_bmacer-0.0.8.dist-info/top_level.txt
a4e_bmacer-0.0.8.dist-info/RECORD
